trickler/.gitignore
trickler/__init__.py
trickler/ChannelPub.py
trickler-0.1.2.dist-info/METADATA
trickler-0.1.2.dist-info/WHEEL
trickler-0.1.2.dist-info/RECORD
