Metadata-Version: 2.4
Name: trickler
Version: 0.1.2
Summary: Stream simple data to the Trickler mobile app for real-time visualization on the go
Author: Trickler
Author-email: pythonsupport@trickler.com
Requires-Python: >=3.13
Classifier: Programming Language :: Python :: 3
Classifier: Programming Language :: Python :: 3.13
Classifier: Programming Language :: Python :: 3.14
Requires-Dist: httpx (>=0.28.1,<0.29.0)
